neuronest/__init__.py
neuronest/core/__init__.py
neuronest/core/exceptions.py
neuronest/core/fixed_parameters.py
neuronest/core/google/__init__.py
neuronest/core/google/storage_client.py
neuronest/core/google/vertex_ai_manager.py
neuronest/core/path.py
neuronest/core/schemas/__init__.py
neuronest/core/schemas/asset.py
neuronest/core/schemas/bigquery/__init__.py
neuronest/core/schemas/bigquery/base.py
neuronest/core/schemas/environment.py
neuronest/core/schemas/image_name.py
neuronest/core/schemas/training_metrics/__init__.py
neuronest/core/schemas/training_metrics/tables.py
neuronest/core/serialization/__init__.py
neuronest/core/serialization/array.py
neuronest/core/serialization/encoding.py
neuronest/core/serialization/image.py
neuronest/core/services/__init__.py
neuronest/core/services/asset_reader.py
neuronest/core/services/audio_reader.py
neuronest/core/services/reader_common.py
neuronest/core/services/training_metrics_writer.py
neuronest/core/tools.py
neuronest/core/utils.py
neuronest-0.1.12.dist-info/WHEEL
neuronest-0.1.12.dist-info/METADATA
neuronest-0.1.12.dist-info/RECORD
