Metadata-Version: 2.1
Name: neuronest
Version: 0.1.12
Summary: Neuronest core project
Author: Côme Arvis
Author-email: come.arvis@neuronest.net
Requires-Python: >=3.8,<3.11
Classifier: Programming Language :: Python :: 3
Classifier: Programming Language :: Python :: 3.8
Classifier: Programming Language :: Python :: 3.9
Classifier: Programming Language :: Python :: 3.10
Requires-Dist: ffmpeg-python (>=0.2.0,<0.3.0)
Requires-Dist: google-cloud-aiplatform (>=1.18.2,<2.0.0)
Requires-Dist: google-cloud-bigquery (>=2.34.4,<3.0.0)
Requires-Dist: google-cloud-storage (>=2.5.0,<3.0.0)
Requires-Dist: librosa (>=0.9.2,<0.10.0)
Requires-Dist: moviepy (>=1.0.3,<2.0.0)
Requires-Dist: numpy (>=1.23.3,<2.0.0)
Requires-Dist: opencv-contrib-python (==4.5.5.64)
Requires-Dist: opencv-python (==4.5.5.64)
Requires-Dist: opencv-python-headless (==4.5.5.64)
Requires-Dist: pandas (>=1.5.0,<2.0.0)
Requires-Dist: pydantic (>=1.10.2,<2.0.0)
Requires-Dist: tqdm (>=4.64.1,<5.0.0)
